<annotation>
	<folder>X_ray</folder>
	<filename>P00025.jpg</filename>
	<source>
		<database>The X_ray Database</database>
		<annotation>The X_ray Database</annotation>
		<image>X_ray</image>
		<flickrid>0</flickrid>
	</source>
	<owner>
		<flickrid>miaocaijing16@mails.ucas.ac.ac</flickrid>
		<name>MeioJane</name>
	</owner>
	<size>
		<width>476</width>
		<height>641</height>
		<depth>3</depth>
	</size>
	<segmented>0</segmented>
	<object>
		<name>Knife</name>
		<pose>Unspecified</pose>
		<truncated>0</truncated>
		<difficult>0</difficult>
		<bndbox>
			<xmin>102.216</xmin>
			<ymin>378.806</ymin>
			<xmax>320.559</xmax>
			<ymax>603.862</ymax>
		</bndbox>
	</object>
	<object>
		<name>Knife</name>
		<pose>Unspecified</pose>
		<truncated>0</truncated>
		<difficult>0</difficult>
		<bndbox>
			<xmin>272.173</xmin>
			<ymin>251.795</ymin>
			<xmax>381.042</xmax>
			<ymax>511.017</ymax>
		</bndbox>
	</object>
</annotation>
