<annotation>
	<folder>X_ray</folder>
	<filename>P00282.jpg</filename>
	<source>
		<database>The X_ray Database</database>
		<annotation>The X_ray Database</annotation>
		<image>X_ray</image>
		<flickrid>0</flickrid>
	</source>
	<owner>
		<flickrid>miaocaijing16@mails.ucas.ac.ac</flickrid>
		<name>MeioJane</name>
	</owner>
	<size>
		<width>673</width>
		<height>497</height>
		<depth>3</depth>
	</size>
	<segmented>0</segmented>
	<object>
		<name>Knife</name>
		<pose>Unspecified</pose>
		<truncated>0</truncated>
		<difficult>0</difficult>
		<bndbox>
			<xmin>18.813</xmin>
			<ymin>149.733</ymin>
			<xmax>91.501</xmax>
			<ymax>473.964</ymax>
		</bndbox>
	</object>
	<object>
		<name>Gun</name>
		<pose>Unspecified</pose>
		<truncated>0</truncated>
		<difficult>0</difficult>
		<bndbox>
			<xmin>22.234</xmin>
			<ymin>158.948</ymin>
			<xmax>178.726</xmax>
			<ymax>256.851</ymax>
		</bndbox>
	</object>
	<object>
		<name>Gun</name>
		<pose>Unspecified</pose>
		<truncated>0</truncated>
		<difficult>0</difficult>
		<bndbox>
			<xmin>312.128</xmin>
			<ymin>245.908</ymin>
			<xmax>423.297</xmax>
			<ymax>362.816</ymax>
		</bndbox>
	</object>
</annotation>
