<annotation>
	<folder>X_ray</folder>
	<filename>P00310.jpg</filename>
	<source>
		<database>The X_ray Database</database>
		<annotation>The X_ray Database</annotation>
		<image>X_ray</image>
		<flickrid>0</flickrid>
	</source>
	<owner>
		<flickrid>miaocaijing16@mails.ucas.ac.ac</flickrid>
		<name>MeioJane</name>
	</owner>
	<size>
		<width>703</width>
		<height>561</height>
		<depth>3</depth>
	</size>
	<segmented>0</segmented>
	<object>
		<name>Gun</name>
		<pose>Unspecified</pose>
		<truncated>0</truncated>
		<difficult>0</difficult>
		<bndbox>
			<xmin>282.272</xmin>
			<ymin>174.866</ymin>
			<xmax>418.942</xmax>
			<ymax>342.581</ymax>
		</bndbox>
	</object>
	<object>
		<name>Gun</name>
		<pose>Unspecified</pose>
		<truncated>0</truncated>
		<difficult>0</difficult>
		<bndbox>
			<xmin>37.517</xmin>
			<ymin>376.384</ymin>
			<xmax>172.4</xmax>
			<ymax>458.291</ymax>
		</bndbox>
	</object>
	<object>
		<name>Knife</name>
		<pose>Unspecified</pose>
		<truncated>0</truncated>
		<difficult>0</difficult>
		<bndbox>
			<xmin>14.292</xmin>
			<ymin>159.914</ymin>
			<xmax>60.742</xmax>
			<ymax>474.542</ymax>
		</bndbox>
	</object>
</annotation>
