<annotation>
	<folder>X_ray</folder>
	<filename>P00815.jpg</filename>
	<source>
		<database>The X_ray Database</database>
		<annotation>The X_ray Database</annotation>
		<image>X_ray</image>
		<flickrid>0</flickrid>
	</source>
	<owner>
		<flickrid>miaocaijing16@mails.ucas.ac.ac</flickrid>
		<name>MeioJane</name>
	</owner>
	<size>
		<width>590</width>
		<height>512</height>
		<depth>3</depth>
	</size>
	<segmented>0</segmented>
	<object>
		<name>Knife</name>
		<pose>Unspecified</pose>
		<truncated>0</truncated>
		<difficult>0</difficult>
		<bndbox>
			<xmin>38.983</xmin>
			<ymin>325.117</ymin>
			<xmax>346.353</xmax>
			<ymax>364.867</ymax>
		</bndbox>
	</object>
	<object>
		<name>Knife</name>
		<pose>Unspecified</pose>
		<truncated>0</truncated>
		<difficult>0</difficult>
		<bndbox>
			<xmin>123.698</xmin>
			<ymin>360.121</ymin>
			<xmax>421.321</xmax>
			<ymax>444.366</ymax>
		</bndbox>
	</object>
	<object>
		<name>Gun</name>
		<pose>Unspecified</pose>
		<truncated>0</truncated>
		<difficult>0</difficult>
		<bndbox>
			<xmin>355.349</xmin>
			<ymin>333.423</ymin>
			<xmax>500.788</xmax>
			<ymax>427.754</ymax>
		</bndbox>
	</object>
	<object>
		<name>Wrench</name>
		<pose>Unspecified</pose>
		<truncated>0</truncated>
		<difficult>0</difficult>
		<bndbox>
			<xmin>260.14</xmin>
			<ymin>307.912</ymin>
			<xmax>513.532</xmax>
			<ymax>445.553</ymax>
		</bndbox>
	</object>
	<object>
		<name>Pliers</name>
		<pose>Unspecified</pose>
		<truncated>0</truncated>
		<difficult>0</difficult>
		<bndbox>
			<xmin>284.879</xmin>
			<ymin>287.147</ymin>
			<xmax>520.28</xmax>
			<ymax>465.131</ymax>
		</bndbox>
	</object>
</annotation>
