<annotation>
	<folder>X_ray</folder>
	<filename>P00931.jpg</filename>
	<source>
		<database>The X_ray Database</database>
		<annotation>The X_ray Database</annotation>
		<image>X_ray</image>
		<flickrid>0</flickrid>
	</source>
	<owner>
		<flickrid>miaocaijing16@mails.ucas.ac.ac</flickrid>
		<name>MeioJane</name>
	</owner>
	<size>
		<width>670</width>
		<height>513</height>
		<depth>3</depth>
	</size>
	<segmented>0</segmented>
	<object>
		<name>Gun</name>
		<pose>Unspecified</pose>
		<truncated>0</truncated>
		<difficult>0</difficult>
		<bndbox>
			<xmin>51.931</xmin>
			<ymin>23.778</ymin>
			<xmax>272.427</xmax>
			<ymax>184.87</ymax>
		</bndbox>
	</object>
	<object>
		<name>Gun</name>
		<pose>Unspecified</pose>
		<truncated>0</truncated>
		<difficult>0</difficult>
		<bndbox>
			<xmin>91.944</xmin>
			<ymin>374.496</ymin>
			<xmax>303.075</xmax>
			<ymax>513</ymax>
		</bndbox>
	</object>
	<object>
		<name>Wrench</name>
		<pose>Unspecified</pose>
		<truncated>0</truncated>
		<difficult>0</difficult>
		<bndbox>
			<xmin>45.121</xmin>
			<ymin>204.487</ymin>
			<xmax>275.832</xmax>
			<ymax>348.341</ymax>
		</bndbox>
	</object>
</annotation>
