<annotation>
	<folder>X_ray</folder>
	<filename>P01436.jpg</filename>
	<source>
		<database>The X_ray Database</database>
		<annotation>The X_ray Database</annotation>
		<image>X_ray</image>
		<flickrid>0</flickrid>
	</source>
	<owner>
		<flickrid>miaocaijing16@mails.ucas.ac.ac</flickrid>
		<name>MeioJane</name>
	</owner>
	<size>
		<width>595</width>
		<height>611</height>
		<depth>3</depth>
	</size>
	<segmented>0</segmented>
	<object>
		<name>Gun</name>
		<pose>Unspecified</pose>
		<truncated>0</truncated>
		<difficult>0</difficult>
		<bndbox>
			<xmin>431.696</xmin>
			<ymin>140.183</ymin>
			<xmax>571.563</xmax>
			<ymax>324.97</ymax>
		</bndbox>
	</object>
	<object>
		<name>Gun</name>
		<pose>Unspecified</pose>
		<truncated>0</truncated>
		<difficult>0</difficult>
		<bndbox>
			<xmin>297.878</xmin>
			<ymin>111.155</ymin>
			<xmax>451.353</xmax>
			<ymax>268.33</ymax>
		</bndbox>
	</object>
</annotation>
