<annotation>
	<folder>X_ray</folder>
	<filename>P01681.jpg</filename>
	<source>
		<database>The X_ray Database</database>
		<annotation>The X_ray Database</annotation>
		<image>X_ray</image>
		<flickrid>0</flickrid>
	</source>
	<owner>
		<flickrid>miaocaijing16@mails.ucas.ac.ac</flickrid>
		<name>MeioJane</name>
	</owner>
	<size>
		<width>810</width>
		<height>777</height>
		<depth>3</depth>
	</size>
	<segmented>0</segmented>
	<object>
		<name>Gun</name>
		<pose>Unspecified</pose>
		<truncated>0</truncated>
		<difficult>0</difficult>
		<bndbox>
			<xmin>506.379</xmin>
			<ymin>445.672</ymin>
			<xmax>712.224</xmax>
			<ymax>631.144</ymax>
		</bndbox>
	</object>
	<object>
		<name>Pliers</name>
		<pose>Unspecified</pose>
		<truncated>0</truncated>
		<difficult>0</difficult>
		<bndbox>
			<xmin>371.55</xmin>
			<ymin>388.95</ymin>
			<xmax>517.7</xmax>
			<ymax>514.098</ymax>
		</bndbox>
	</object>
	<object>
		<name>Pliers</name>
		<pose>Unspecified</pose>
		<truncated>0</truncated>
		<difficult>0</difficult>
		<bndbox>
			<xmin>162.618</xmin>
			<ymin>158.461</ymin>
			<xmax>404.485</xmax>
			<ymax>402.455</ymax>
		</bndbox>
	</object>
</annotation>
