<annotation>
	<folder>X_ray</folder>
	<filename>P01792.jpg</filename>
	<source>
		<database>The X_ray Database</database>
		<annotation>The X_ray Database</annotation>
		<image>X_ray</image>
		<flickrid>0</flickrid>
	</source>
	<owner>
		<flickrid>miaocaijing16@mails.ucas.ac.ac</flickrid>
		<name>MeioJane</name>
	</owner>
	<size>
		<width>567</width>
		<height>676</height>
		<depth>3</depth>
	</size>
	<segmented>0</segmented>
	<object>
		<name>Gun</name>
		<pose>Unspecified</pose>
		<truncated>0</truncated>
		<difficult>0</difficult>
		<bndbox>
			<xmin>48.271</xmin>
			<ymin>553.02</ymin>
			<xmax>244.956</xmax>
			<ymax>650.934</ymax>
		</bndbox>
	</object>
	<object>
		<name>Gun</name>
		<pose>Unspecified</pose>
		<truncated>0</truncated>
		<difficult>0</difficult>
		<bndbox>
			<xmin>1.441</xmin>
			<ymin>321.942</ymin>
			<xmax>85.014</xmax>
			<ymax>468.422</ymax>
		</bndbox>
	</object>
</annotation>
