<annotation>
	<folder>X_ray</folder>
	<filename>P01757.jpg</filename>
	<source>
		<database>The X_ray Database</database>
		<annotation>The X_ray Database</annotation>
		<image>X_ray</image>
		<flickrid>0</flickrid>
	</source>
	<owner>
		<flickrid>miaocaijing16@mails.ucas.ac.ac</flickrid>
		<name>MeioJane</name>
	</owner>
	<size>
		<width>601</width>
		<height>607</height>
		<depth>3</depth>
	</size>
	<segmented>0</segmented>
	<object>
		<name>Gun</name>
		<pose>Unspecified</pose>
		<truncated>0</truncated>
		<difficult>0</difficult>
		<bndbox>
			<xmin>263.463</xmin>
			<ymin>204.678</ymin>
			<xmax>474.233</xmax>
			<ymax>384.035</ymax>
		</bndbox>
	</object>
	<object>
		<name>Gun</name>
		<pose>Unspecified</pose>
		<truncated>0</truncated>
		<difficult>0</difficult>
		<bndbox>
			<xmin>232.916</xmin>
			<ymin>211.008</ymin>
			<xmax>407.794</xmax>
			<ymax>370.671</ymax>
		</bndbox>
	</object>
</annotation>
