<annotation>
	<folder>X_ray</folder>
	<filename>P02581.jpg</filename>
	<source>
		<database>The X_ray Database</database>
		<annotation>The X_ray Database</annotation>
		<image>X_ray</image>
		<flickrid>0</flickrid>
	</source>
	<owner>
		<flickrid>miaocaijing16@mails.ucas.ac.ac</flickrid>
		<name>MeioJane</name>
	</owner>
	<size>
		<width>862</width>
		<height>608</height>
		<depth>3</depth>
	</size>
	<segmented>0</segmented>
	<object>
		<name>Gun</name>
		<pose>Unspecified</pose>
		<truncated>0</truncated>
		<difficult>0</difficult>
		<bndbox>
			<xmin>78.861</xmin>
			<ymin>228.969</ymin>
			<xmax>151.151</xmax>
			<ymax>443.143</ymax>
		</bndbox>
	</object>
	<object>
		<name>Gun</name>
		<pose>Unspecified</pose>
		<truncated>0</truncated>
		<difficult>0</difficult>
		<bndbox>
			<xmin>123.769</xmin>
			<ymin>215.583</ymin>
			<xmax>257.395</xmax>
			<ymax>407.917</ymax>
		</bndbox>
	</object>
	<object>
		<name>Gun</name>
		<pose>Unspecified</pose>
		<truncated>0</truncated>
		<difficult>0</difficult>
		<bndbox>
			<xmin>97.482</xmin>
			<ymin>179.652</ymin>
			<xmax>222.346</xmax>
			<ymax>305.761</ymax>
		</bndbox>
	</object>
</annotation>
