<annotation>
	<folder>X_ray</folder>
	<filename>P02781.jpg</filename>
	<source>
		<database>The X_ray Database</database>
		<annotation>The X_ray Database</annotation>
		<image>X_ray</image>
		<flickrid>0</flickrid>
	</source>
	<owner>
		<flickrid>miaocaijing16@mails.ucas.ac.ac</flickrid>
		<name>MeioJane</name>
	</owner>
	<size>
		<width>830</width>
		<height>601</height>
		<depth>3</depth>
	</size>
	<segmented>0</segmented>
	<object>
		<name>Gun</name>
		<pose>Unspecified</pose>
		<truncated>0</truncated>
		<difficult>0</difficult>
		<bndbox>
			<xmin>45.349</xmin>
			<ymin>432.469</ymin>
			<xmax>196.163</xmax>
			<ymax>520.913</ymax>
		</bndbox>
	</object>
	<object>
		<name>Knife</name>
		<pose>Unspecified</pose>
		<truncated>0</truncated>
		<difficult>0</difficult>
		<bndbox>
			<xmin>27.421</xmin>
			<ymin>169.924</ymin>
			<xmax>446.112</xmax>
			<ymax>293.884</ymax>
		</bndbox>
	</object>
	<object>
		<name>Knife</name>
		<pose>Unspecified</pose>
		<truncated>0</truncated>
		<difficult>0</difficult>
		<bndbox>
			<xmin>17.929</xmin>
			<ymin>142.067</ymin>
			<xmax>451.385</xmax>
			<ymax>286.92</ymax>
		</bndbox>
	</object>
</annotation>
