<annotation>
	<folder>X_ray</folder>
	<filename>P04827.jpg</filename>
	<source>
		<database>The X_ray Database</database>
		<annotation>The X_ray Database</annotation>
		<image>X_ray</image>
		<flickrid>0</flickrid>
	</source>
	<owner>
		<flickrid>miaocaijing16@mails.ucas.ac.ac</flickrid>
		<name>MeioJane</name>
	</owner>
	<size>
		<width>314</width>
		<height>250</height>
		<depth>3</depth>
	</size>
	<segmented>0</segmented>
	<object>
		<name>Scissors</name>
		<pose>Unspecified</pose>
		<truncated>0</truncated>
		<difficult>0</difficult>
		<bndbox>
			<xmin>152.013</xmin>
			<ymin>101.68</ymin>
			<xmax>223.431</xmax>
			<ymax>163.963</ymax>
		</bndbox>
	</object>
</annotation>
