<annotation>
	<folder>X_ray</folder>
	<filename>P05640.jpg</filename>
	<source>
		<database>The X_ray Database</database>
		<annotation>The X_ray Database</annotation>
		<image>X_ray</image>
		<flickrid>0</flickrid>
	</source>
	<owner>
		<flickrid>miaocaijing16@mails.ucas.ac.ac</flickrid>
		<name>MeioJane</name>
	</owner>
	<size>
		<width>573</width>
		<height>634</height>
		<depth>3</depth>
	</size>
	<segmented>0</segmented>
	<object>
		<name>Wrench</name>
		<pose>Unspecified</pose>
		<truncated>0</truncated>
		<difficult>0</difficult>
		<bndbox>
			<xmin>94.651</xmin>
			<ymin>326.918</ymin>
			<xmax>240.995</xmax>
			<ymax>589.187</ymax>
		</bndbox>
	</object>
</annotation>
