<annotation>
	<folder>X_ray</folder>
	<filename>P06178.jpg</filename>
	<source>
		<database>The X_ray Database</database>
		<annotation>The X_ray Database</annotation>
		<image>X_ray</image>
		<flickrid>0</flickrid>
	</source>
	<owner>
		<flickrid>miaocaijing16@mails.ucas.ac.ac</flickrid>
		<name>MeioJane</name>
	</owner>
	<size>
		<width>298</width>
		<height>316</height>
		<depth>3</depth>
	</size>
	<segmented>0</segmented>
	<object>
		<name>Pliers</name>
		<pose>Unspecified</pose>
		<truncated>0</truncated>
		<difficult>0</difficult>
		<bndbox>
			<xmin>187.433</xmin>
			<ymin>182.35</ymin>
			<xmax>260.892</xmax>
			<ymax>283.045</ymax>
		</bndbox>
	</object>
	<object>
		<name>Pliers</name>
		<pose>Unspecified</pose>
		<truncated>0</truncated>
		<difficult>0</difficult>
		<bndbox>
			<xmin>112.081</xmin>
			<ymin>122.665</ymin>
			<xmax>241.581</xmax>
			<ymax>228.121</ymax>
		</bndbox>
	</object>
</annotation>
