<annotation>
	<folder>X_ray</folder>
	<filename>P07813.jpg</filename>
	<source>
		<database>The X_ray Database</database>
		<annotation>The X_ray Database</annotation>
		<image>X_ray</image>
		<flickrid>0</flickrid>
	</source>
	<owner>
		<flickrid>miaocaijing16@mails.ucas.ac.ac</flickrid>
		<name>MeioJane</name>
	</owner>
	<size>
		<width>249</width>
		<height>199</height>
		<depth>3</depth>
	</size>
	<segmented>0</segmented>
	<object>
		<name>Pliers</name>
		<pose>Unspecified</pose>
		<truncated>0</truncated>
		<difficult>0</difficult>
		<bndbox>
			<xmin>113.584</xmin>
			<ymin>48.424</ymin>
			<xmax>241.723</xmax>
			<ymax>140.66</ymax>
		</bndbox>
	</object>
</annotation>
