<annotation>
	<folder>X_ray</folder>
	<filename>P08256.jpg</filename>
	<source>
		<database>The X_ray Database</database>
		<annotation>The X_ray Database</annotation>
		<image>X_ray</image>
		<flickrid>0</flickrid>
	</source>
	<owner>
		<flickrid>miaocaijing16@mails.ucas.ac.ac</flickrid>
		<name>MeioJane</name>
	</owner>
	<size>
		<width>434</width>
		<height>775</height>
		<depth>3</depth>
	</size>
	<segmented>0</segmented>
	<object>
		<name>Pliers</name>
		<pose>Unspecified</pose>
		<truncated>0</truncated>
		<difficult>0</difficult>
		<bndbox>
			<xmin>194.666</xmin>
			<ymin>593.598</ymin>
			<xmax>265.804</xmax>
			<ymax>715.73</ymax>
		</bndbox>
	</object>
	<object>
		<name>Pliers</name>
		<pose>Unspecified</pose>
		<truncated>0</truncated>
		<difficult>0</difficult>
		<bndbox>
			<xmin>288.414</xmin>
			<ymin>533.43</ymin>
			<xmax>403.118</xmax>
			<ymax>704.954</ymax>
		</bndbox>
	</object>
	<object>
		<name>Wrench</name>
		<pose>Unspecified</pose>
		<truncated>0</truncated>
		<difficult>0</difficult>
		<bndbox>
			<xmin>297.238</xmin>
			<ymin>529.838</ymin>
			<xmax>327.017</xmax>
			<ymax>593.598</ymax>
		</bndbox>
	</object>
	<object>
		<name>Wrench</name>
		<pose>Unspecified</pose>
		<truncated>0</truncated>
		<difficult>0</difficult>
		<bndbox>
			<xmin>234.922</xmin>
			<ymin>524.45</ymin>
			<xmax>410.287</xmax>
			<ymax>775</ymax>
		</bndbox>
	</object>
	<object>
		<name>Wrench</name>
		<pose>Unspecified</pose>
		<truncated>0</truncated>
		<difficult>0</difficult>
		<bndbox>
			<xmin>142.828</xmin>
			<ymin>498.407</ymin>
			<xmax>329.774</xmax>
			<ymax>610.66</ymax>
		</bndbox>
	</object>
</annotation>
