<annotation>
	<folder>X_ray</folder>
	<filename>P08765.jpg</filename>
	<source>
		<database>The X_ray Database</database>
		<annotation>The X_ray Database</annotation>
		<image>X_ray</image>
		<flickrid>0</flickrid>
	</source>
	<owner>
		<flickrid>miaocaijing16@mails.ucas.ac.ac</flickrid>
		<name>MeioJane</name>
	</owner>
	<size>
		<width>599</width>
		<height>768</height>
		<depth>3</depth>
	</size>
	<segmented>0</segmented>
	<object>
		<name>Wrench</name>
		<pose>Unspecified</pose>
		<truncated>0</truncated>
		<difficult>0</difficult>
		<bndbox>
			<xmin>306.731</xmin>
			<ymin>80.093</ymin>
			<xmax>433.837</xmax>
			<ymax>98.781</ymax>
		</bndbox>
	</object>
	<object>
		<name>Wrench</name>
		<pose>Unspecified</pose>
		<truncated>0</truncated>
		<difficult>0</difficult>
		<bndbox>
			<xmin>331.848</xmin>
			<ymin>134.378</ymin>
			<xmax>481.788</xmax>
			<ymax>169.085</ymax>
		</bndbox>
	</object>
	<object>
		<name>Wrench</name>
		<pose>Unspecified</pose>
		<truncated>0</truncated>
		<difficult>0</difficult>
		<bndbox>
			<xmin>298.358</xmin>
			<ymin>142.387</ymin>
			<xmax>465.804</xmax>
			<ymax>184.213</ymax>
		</bndbox>
	</object>
	<object>
		<name>Wrench</name>
		<pose>Unspecified</pose>
		<truncated>0</truncated>
		<difficult>0</difficult>
		<bndbox>
			<xmin>319.67</xmin>
			<ymin>97.001</ymin>
			<xmax>495.488</xmax>
			<ymax>135.268</ymax>
		</bndbox>
	</object>
</annotation>
