<annotation>
	<folder>X_ray</folder>
	<filename>P07726.jpg</filename>
	<source>
		<database>The X_ray Database</database>
		<annotation>The X_ray Database</annotation>
		<image>X_ray</image>
		<flickrid>0</flickrid>
	</source>
	<owner>
		<flickrid>miaocaijing16@mails.ucas.ac.ac</flickrid>
		<name>MeioJane</name>
	</owner>
	<size>
		<width>910</width>
		<height>492</height>
		<depth>3</depth>
	</size>
	<segmented>0</segmented>
	<object>
		<name>Pliers</name>
		<pose>Unspecified</pose>
		<truncated>0</truncated>
		<difficult>0</difficult>
		<bndbox>
			<xmin>489.111</xmin>
			<ymin>159.059</ymin>
			<xmax>578.145</xmax>
			<ymax>322.109</ymax>
		</bndbox>
	</object>
	<object>
		<name>Pliers</name>
		<pose>Unspecified</pose>
		<truncated>0</truncated>
		<difficult>0</difficult>
		<bndbox>
			<xmin>612.834</xmin>
			<ymin>203.527</ymin>
			<xmax>705.337</xmax>
			<ymax>350.044</ymax>
		</bndbox>
	</object>
	<object>
		<name>Pliers</name>
		<pose>Unspecified</pose>
		<truncated>0</truncated>
		<difficult>0</difficult>
		<bndbox>
			<xmin>764.307</xmin>
			<ymin>129.414</ymin>
			<xmax>862.592</xmax>
			<ymax>239.444</ymax>
		</bndbox>
	</object>
	<object>
		<name>Pliers</name>
		<pose>Unspecified</pose>
		<truncated>0</truncated>
		<difficult>0</difficult>
		<bndbox>
			<xmin>418.577</xmin>
			<ymin>189.275</ymin>
			<xmax>465.985</xmax>
			<ymax>360.876</ymax>
		</bndbox>
	</object>
</annotation>
